datafusion-51.0.0.dist-info/METADATA
datafusion-51.0.0.dist-info/WHEEL
datafusion-51.0.0.dist-info/licenses/LICENSE.txt
datafusion/catalog.py
datafusion/col.py
datafusion/common.py
datafusion/context.py
datafusion/dataframe.py
datafusion/dataframe_formatter.py
datafusion/expr.py
datafusion/functions.py
datafusion/html_formatter.py
datafusion/input/base.py
datafusion/input/location.py
datafusion/input/__init__.py
datafusion/io.py
datafusion/object_store.py
datafusion/plan.py
datafusion/py.typed
datafusion/record_batch.py
datafusion/substrait.py
datafusion/udf.py
datafusion/unparser.py
datafusion/user_defined.py
datafusion/__init__.py
datafusion/_internal.pyd
datafusion-51.0.0.dist-info/RECORD
