Metadata-Version: 2.4
Name: datafusion
Version: 51.0.0
Classifier: Development Status :: 2 - Pre-Alpha
Classifier: Intended Audience :: Developers
Classifier: License :: OSI Approved :: Apache Software License
Classifier: License :: OSI Approved
Classifier: Operating System :: MacOS
Classifier: Operating System :: Microsoft :: Windows
Classifier: Operating System :: POSIX :: Linux
Classifier: Programming Language :: Python :: 3
Classifier: Programming Language :: Python :: 3.10
Classifier: Programming Language :: Python :: 3.11
Classifier: Programming Language :: Python :: 3.12
Classifier: Programming Language :: Python :: 3.13
Classifier: Programming Language :: Python :: 3.14
Classifier: Programming Language :: Python
Classifier: Programming Language :: Rust
Requires-Dist: pyarrow >=16.0.0 ; python_version < '3.14'
Requires-Dist: pyarrow >=22.0.0 ; python_version >= '3.14'
Requires-Dist: typing-extensions ; python_version < '3.13'
License-File: LICENSE.txt
Summary: Build and run queries against data
Keywords: datafusion,dataframe,rust,query-engine
Home-Page: https://datafusion.apache.org/python
Author: Apache DataFusion <dev@datafusion.apache.org>
Author-email: Apache DataFusion <dev@datafusion.apache.org>
License: Apache-2.0
Requires-Python: >=3.10
Project-URL: homepage, https://datafusion.apache.org/python
Project-URL: documentation, https://datafusion.apache.org/python
Project-URL: repository, https://github.com/apache/datafusion-python
